README.txt
setup.py
docs/HISTORY.txt
docs/INSTALL.txt
docs/LICENSE.GPL
docs/LICENSE.txt
fourdigits/__init__.py
fourdigits.pfg.activationcode.egg-info/PKG-INFO
fourdigits.pfg.activationcode.egg-info/SOURCES.txt
fourdigits.pfg.activationcode.egg-info/dependency_links.txt
fourdigits.pfg.activationcode.egg-info/entry_points.txt
fourdigits.pfg.activationcode.egg-info/namespace_packages.txt
fourdigits.pfg.activationcode.egg-info/not-zip-safe
fourdigits.pfg.activationcode.egg-info/requires.txt
fourdigits.pfg.activationcode.egg-info/top_level.txt
fourdigits/pfg/__init__.py
fourdigits/pfg/activationcode/__init__.py
fourdigits/pfg/activationcode/config.py
fourdigits/pfg/activationcode/configure.zcml
fourdigits/pfg/activationcode/tests.py
fourdigits/pfg/activationcode/version.txt
fourdigits/pfg/activationcode/content/__init__.py
fourdigits/pfg/activationcode/content/activationcode.py
fourdigits/pfg/activationcode/content/configure.zcml
fourdigits/pfg/activationcode/content/interfaces.py
fourdigits/pfg/activationcode/profiles/default/factorytool.xml
fourdigits/pfg/activationcode/profiles/default/fouridigspfgactivationcode.txt
fourdigits/pfg/activationcode/profiles/default/metadata.xml
fourdigits/pfg/activationcode/profiles/default/rolemap.xml
fourdigits/pfg/activationcode/profiles/default/types.xml
fourdigits/pfg/activationcode/profiles/default/workflows.xml
fourdigits/pfg/activationcode/profiles/default/types/FieldsetFolder.xml
fourdigits/pfg/activationcode/profiles/default/types/FormActivationCodeField.xml
fourdigits/pfg/activationcode/profiles/default/types/FormFolder.xml