Metadata-Version: 1.0
Name: fourdigits.pfg.activationcode
Version: 0.1
Summary: A PFG field to provide a list of activation codes and let PFG check them when submitting a form
Home-page: http://svn.plone.org/svn/collective/
Author: Maarten Kling (Four Digits)
Author-email: info@fourdigits.nl
License: GPL
Keywords: PFG Activation Code Field
Platform: UNKNOWN
Classifier: Framework :: Plone
Classifier: Programming Language :: Python
